<?xml version="1.0" encoding="UTF-8"?>
  <?xml-stylesheet type="text/xsl" href="rfc2629.xslt" ?>
  <!-- generated by https://github.com/cabo/kramdown-rfc2629 version 1.4.7 -->

<!DOCTYPE rfc SYSTEM "rfc2629.dtd" [
]>

<?rfc toc="yes"?>
<?rfc sortrefs="yes"?>
<?rfc symrefs="yes"?>

<rfc ipr="trust200902" docName="draft-ietf-pce-multipath-00" category="std">

  <front>
    <title abbrev="PCEP Extensions for Multipath">PCEP Extensions for Signaling Multipath Information</title>

    <author initials="M." surname="Koldychev" fullname="Mike Koldychev">
      <organization>Cisco Systems, Inc.</organization>
      <address>
        <email>mkoldych@cisco.com</email>
      </address>
    </author>
    <author initials="S." surname="Sivabalan" fullname="Siva Sivabalan">
      <organization>Ciena Corporation</organization>
      <address>
        <email>ssivabal@ciena.com</email>
      </address>
    </author>
    <author initials="T." surname="Saad" fullname="Tarek Saad">
      <organization>Juniper Networks, Inc.</organization>
      <address>
        <email>tsaad@juniper.net</email>
      </address>
    </author>
    <author initials="V." surname="Beeram" fullname="Vishnu Pavan Beeram">
      <organization>Juniper Networks, Inc.</organization>
      <address>
        <email>vbeeram@juniper.net</email>
      </address>
    </author>
    <author initials="H." surname="Bidgoli" fullname="Hooman Bidgoli">
      <organization>Nokia</organization>
      <address>
        <email>hooman.bidgoli@nokia.com</email>
      </address>
    </author>
    <author initials="B." surname="Yadav" fullname="Bhupendra Yadav">
      <organization>Ciena</organization>
      <address>
        <email>byadav@ciena.com</email>
      </address>
    </author>
    <author initials="S." surname="Peng" fullname="Shuping Peng">
      <organization>Huawei Technologies</organization>
      <address>
        <email>pengshuping@huawei.com</email>
      </address>
    </author>

    <date year="2021" month="July" day="27"/>

    <area>Routing</area>
    <workgroup>PCE Working Group</workgroup>
    

    <abstract>


<t>Current PCEP standards allow only one intended and/or actual path to be present
in a PCEP report or update. Applications that require multipath support such as
SR Policy require an extension to allow signaling multiple intended and/or
actual paths within a single PCEP message. This document introduces such an
extension. Encoding of multiple intended and/or actual paths is done by
encoding multiple Explicit Route Objects (EROs) and/or multiple Record Route
Objects (RROs). A special separator object is defined in this document, to
facilitate this. This mechanism is applicable to SR-TE and RSVP-TE and is
dataplane agnostic.</t>



    </abstract>


  </front>

  <middle>


<section anchor="introduction" title="Introduction">

<t>Path Computation Element (PCE) Communication Protocol (PCEP)
<xref target="RFC5440"/> enables the communication between a Path Computation Client
(PCC) and a Path Control Element (PCE), or between two PCEs based on
the PCE architecture <xref target="RFC4655"/>.</t>

<t>PCEP Extensions for the Stateful PCE Model <xref target="RFC8231"/> describes a set
of extensions to PCEP that enable active control of Multiprotocol Label
Switching Traffic Engineering (MPLS-TE) and Generalized MPLS (GMPLS)
tunnels.  <xref target="RFC8281"/> describes the setup and teardown of PCE-initiated
LSPs under the active stateful PCE model, without the need for local
configuration on the PCC, thus allowing for dynamic centralized
control of a network.</t>

<t>PCEP Extensions for Segment Routing <xref target="RFC8664"/>
specifies extensions to the Path Computation Element Protocol (PCEP)
that allow a stateful PCE to compute and initiate Traffic Engineering
(TE) paths, as well as for a PCC to request a path subject to certain
constraint(s) and optimization criteria in SR networks.</t>

<t>Segment Routing Policy for Traffic Engineering
<xref target="I-D.ietf-spring-segment-routing-policy"/> details the concepts of SR
Policy and approaches to steering traffic into an SR Policy.  In
particular, it describes the SR candidate-path as a collection of one
or more Segment-Lists.  The current PCEP standards only allow for
signaling of one Segment-List per Candidate-Path.  PCEP extension to
support Segment Routing Policy Candidate Paths
<xref target="I-D.ietf-pce-segment-routing-policy-cp"/> specifically avoids
defining how to signal multipath information, and states that this
will be defined in another document.</t>

<t>This document defines the required extensions that allow the signaling
of multipath information via PCEP.</t>

</section>
<section anchor="terminology" title="Terminology">

<t>The key words “MUST”, “MUST NOT”, “REQUIRED”, “SHALL”, “SHALL
NOT”, “SHOULD”, “SHOULD NOT”, “RECOMMENDED”, “NOT RECOMMENDED”,
“MAY”, and “OPTIONAL” in this document are to be interpreted as
described in BCP 14 <xref target="RFC2119"/> <xref target="RFC8174"/> when, and only when, 
they appear in all capitals, as shown here.</t>

<section anchor="terms-and-abbreviations" title="Terms and Abbreviations">

<t>The following terms are used in this document:</t>

<t>PCEP Tunnel:</t>

<t><list style='empty'>
  <t>The object identified by the PLSP-ID, see <xref target="I-D.koldychev-pce-operational"/> for more details.</t>
</list></t>

</section>
</section>
<section anchor="motivation" title="Motivation">

<t>This extension is motivated by the use-cases described below.</t>

<section anchor="signaling-multiple-segment-lists-of-an-sr-candidate-path" title="Signaling Multiple Segment-Lists of an SR Candidate-Path">

<t>The Candidate-Path of an SR Policy is the unit of report/update in PCEP, see
<xref target="I-D.ietf-pce-segment-routing-policy-cp"/>.  Each Candidate-Path can
contain multiple Segment-Lists and each Segment-List is encoded by
one ERO.  However, each PCEP LSP can contain only a
single ERO (containing multiple SR-ERO subobject), which prevents us from encoding multiple Segment-
Lists within the same SR Candidate-Path.</t>

<t>With the help of the protocol extensions defined in this document,
this limitation is overcome.</t>

</section>
<section anchor="splitting-of-requested-bandwidth" title="Splitting of Requested Bandwidth">

<t>A PCC may request a path with 80 Gbps of bandwidth, but all links in the
network have only 50 Gbps capacity.  The PCE can return two paths, that can
together carry 80 Gbps. The PCC can then equally or unequally split the incoming
80 Gbps of traffic among the two paths. <xref target="WEIGHT-TLV"/> introduces a
new TLV that carries the path weight that allows for distribution of incoming
traffic on to the multiple paths.</t>

</section>
<section anchor="providing-backup-path-for-protection" title="Providing Backup path for Protection">

<t>It is desirable for the PCE to compute and signal to the PCC a backup path
that is used to protect a primary path within the multipaths in a given LSP.</t>

<t>Note that <xref target="RFC8745"/> specify the Path Protection association among LSPs. The use of <xref target="RFC8745"/> with multipath is out of scope of this document and is for future study.</t>

<t>When multipath is used, a backup path may protect one or more primary
paths.  For this reason, primary and backup path identifiers are needed to
indicate which backup path(s) protect which primary path(s).
<xref target="BACKUP-TLV"/> introduces a new TLV that carries the required information.</t>

</section>
</section>
<section anchor="protocol-extensions" title="Protocol Extensions">

<section anchor="multipath-capability-tlv" title="Multipath Capability TLV">

<t>We define the MULTIPATH-CAP TLV that MAY be present in the OPEN
object and/or the LSP object.  The purpose of this TLV is two-fold:</t>

<t><list style="numbers">
  <t>From PCC: it tells how many multipaths per PCEP Tunnel, the PCC can install in
forwarding.</t>
  <t>From PCE: it tells that the PCE supports this standard and how
many multipaths per PCEP Tunnel, the PCE can compute.</t>
</list></t>

<t>Only the first instance of this TLV can be processed, subsequent
instances SHOULD be ignored.</t>

<t><xref target="OP"/> specify the usage of this TLV with Open message (within the OPEN object) and other PCEP messages (within the LSP object).</t>

<figure title="MULTIPATH-CAP TLV format" anchor="fig-multipath-cap"><artwork><![CDATA[
   0                   1                   2                   3
   0 1 2 3 4 5 6 7 8 9 0 1 2 3 4 5 6 7 8 9 0 1 2 3 4 5 6 7 8 9 0 1
  +-+-+-+-+-+-+-+-+-+-+-+-+-+-+-+-+-+-+-+-+-+-+-+-+-+-+-+-+-+-+-+-+
  |             Type              |             Length            |
  +-+-+-+-+-+-+-+-+-+-+-+-+-+-+-+-+-+-+-+-+-+-+-+-+-+-+-+-+-+-+-+-+
  |     Number of Multipaths      |            Flags        |O|B|W|
  +-+-+-+-+-+-+-+-+-+-+-+-+-+-+-+-+-+-+-+-+-+-+-+-+-+-+-+-+-+-+-+-+
]]></artwork></figure>

<t>Type: TBD1 for “MULTIPATH-CAP” TLV.</t>

<t>Length: 4.</t>

<t>Number of Multipaths: the maximum number of multipaths per PCEP 
Tunnel. The value 0 indicates unlimited number.</t>

<t>W-flag: whether MULTIPATH-WEIGHT-TLV is supported.</t>

<t>B-flag: whether MULTIPATH-BACKUP-TLV is supported.</t>

<t>O-flag: whether MULTIPATH-OPPDIR-PATH-TLV is supported.</t>

</section>
<section anchor="path-attributes-object" title="Path Attributes Object">

<t>We define the PATH-ATTRIB object that is used to carry per-path
information and to act as a separator between several ERO/RRO objects
in the &lt;intended-path&gt;/&lt;actual-path&gt; RBNF element.
The PATH-ATTRIB object always precedes the ERO/RRO that it applies to.  If
multiple ERO/RRO objects are present, then each ERO/RRO object MUST be
preceded by an PATH-ATTRIB object that describes it.</t>

<t>The PATH-ATTRIB Object-Class value is TBD2.</t>

<t>The PATH-ATTRIB Object-Type value is 1.</t>

<figure title="PATH-ATTRIB object format" anchor="fig-path-attrib"><artwork><![CDATA[
   0                   1                   2                   3
   0 1 2 3 4 5 6 7 8 9 0 1 2 3 4 5 6 7 8 9 0 1 2 3 4 5 6 7 8 9 0 1
  +-+-+-+-+-+-+-+-+-+-+-+-+-+-+-+-+-+-+-+-+-+-+-+-+-+-+-+-+-+-+-+-+
  |                         Flags                           |  O  |
  +-+-+-+-+-+-+-+-+-+-+-+-+-+-+-+-+-+-+-+-+-+-+-+-+-+-+-+-+-+-+-+-+
  |                         Path ID                               |
  +-+-+-+-+-+-+-+-+-+-+-+-+-+-+-+-+-+-+-+-+-+-+-+-+-+-+-+-+-+-+-+-+
  ~                          Optional TLVs                        ~
  +-+-+-+-+-+-+-+-+-+-+-+-+-+-+-+-+-+-+-+-+-+-+-+-+-+-+-+-+-+-+-+-+
]]></artwork></figure>

<t>O (Operational - 3 bits): operational state of the path, same 
values as the identically named field in the LSP object <xref target="RFC8231"/>.</t>

<t>Path ID: 4-octet identifier that identifies a path in the set of
multiple paths. It uniquely identifies a path (encoded in the 
ERO/RRO) within the set of multiple paths under the PCEP LSP. Once a 
path changes, a new Path ID is assigned.
Value 0x0 is reserved to indicate the absense of a Path ID.</t>

<t>TLVs that may be included in the PATH-ATTRIB object are described in the
following sections.  Other optional TLVs could be defined by future
documents to be included within the PATH-ATTRIB object body.</t>

</section>
<section anchor="WEIGHT-TLV" title="Multipath Weight TLV">

<t>We define the MULTIPATH-WEIGHT TLV that MAY be present in the
PATH-ATTRIB object.</t>

<figure title="MULTIPATH-WEIGHT TLV format" anchor="fig-multipath-path-attrib"><artwork><![CDATA[
   0                   1                   2                   3
   0 1 2 3 4 5 6 7 8 9 0 1 2 3 4 5 6 7 8 9 0 1 2 3 4 5 6 7 8 9 0 1
  +-+-+-+-+-+-+-+-+-+-+-+-+-+-+-+-+-+-+-+-+-+-+-+-+-+-+-+-+-+-+-+-+
  |             Type              |             Length            |
  +-+-+-+-+-+-+-+-+-+-+-+-+-+-+-+-+-+-+-+-+-+-+-+-+-+-+-+-+-+-+-+-+
  |                             Weight                            |
  +-+-+-+-+-+-+-+-+-+-+-+-+-+-+-+-+-+-+-+-+-+-+-+-+-+-+-+-+-+-+-+-+
]]></artwork></figure>

<t>Type: TBD3 for “MULTIPATH-WEIGHT” TLV.</t>

<t>Length: 4.</t>

<t>Weight: weight of this path within the multipath, if W-ECMP is
desired. The fraction of flows a specific ERO/RRO carries is derived
from the ratio of its weight to the sum of all other multipath ERO/RRO weights.</t>

<t>When the MULTIPATH-WEIGHT TLV is absent from the PATH-ATTRIB object,
or the PATH-ATTRIB object is absent from the
&lt;intended-path&gt;/&lt;actual-path&gt;, then the Weight of the corresponding
path is taken to be “1”.</t>

</section>
<section anchor="BACKUP-TLV" title="Multipath Backup TLV">

<t>This document introduces a new MULTIPATH-BACKUP TLV that is optional and can
be present in the PATH-ATTRIB object.</t>

<t>This TLV is used to indicate the presence of a backup path that is
used for protection in case of failure of the primary path. The format of
the MULTIPATH-BACKUP TLV is:</t>

<figure title="MULTIPATH-BACKUP TLV format" anchor="fig-multipath-backup"><artwork><![CDATA[
   0                   1                   2                   3
   0 1 2 3 4 5 6 7 8 9 0 1 2 3 4 5 6 7 8 9 0 1 2 3 4 5 6 7 8 9 0 1
  +-+-+-+-+-+-+-+-+-+-+-+-+-+-+-+-+-+-+-+-+-+-+-+-+-+-+-+-+-+-+-+-+
  |             Type              |             Length            |
  +-+-+-+-+-+-+-+-+-+-+-+-+-+-+-+-+-+-+-+-+-+-+-+-+-+-+-+-+-+-+-+-+
  |       Backup Path Count       |             Flags           |B|
  +-+-+-+-+-+-+-+-+-+-+-+-+-+-+-+-+-+-+-+-+-+-+-+-+-+-+-+-+-+-+-+-+
  |                         Backup Path ID 1                      |
  +-+-+-+-+-+-+-+-+-+-+-+-+-+-+-+-+-+-+-+-+-+-+-+-+-+-+-+-+-+-+-+-+
  |                         Backup Path ID 2                      |
  +-+-+-+-+-+-+-+-+-+-+-+-+-+-+-+-+-+-+-+-+-+-+-+-+-+-+-+-+-+-+-+-+
  |                              ...                              |
  +-+-+-+-+-+-+-+-+-+-+-+-+-+-+-+-+-+-+-+-+-+-+-+-+-+-+-+-+-+-+-+-+
  |                         Backup Path ID n                      |
  +-+-+-+-+-+-+-+-+-+-+-+-+-+-+-+-+-+-+-+-+-+-+-+-+-+-+-+-+-+-+-+-+

]]></artwork></figure>

<t>Type: TBD4 for “MULTIPATH-BACKUP” TLV</t>

<t>Length: 4 + (N * 4) (where N is the Backup Path Count)</t>

<t>Backup Path Count: Number of backup path(s).</t>

<t>B: If set, indicates a pure backup path. This is a path that only
carries rerouted traffic after the protected path fails. If this flag
is not set, or if the MULTIPATH-BACKUP TLV is absent,
then the path is assumed to be primary that
carries normal traffic.</t>

<t>Backup Path ID(s): a series of 4-octet identifier(s) that identify the
backup path(s) in the set that protect this primary path.</t>

</section>
<section anchor="OPPDIR-PATH-TLV" title="Multipath Opposite Direction Path TLV">

<t>This document introduces a new MULTIPATH-OPPDIR-PATH TLV that is optional
and can be present in the PATH-ATTRIB object.</t>

<t>This TLV is used to indicate whether the given path is a forward path or a
reverse path in its PCEP Tunnel, as well as give information about the
opposite-direction path(s) of the given path.</t>

<figure title="MULTIPATH-OPPDIR-PATH TLV format" anchor="fig-multipath-oppdir"><artwork><![CDATA[
   0                   1                   2                   3
   0 1 2 3 4 5 6 7 8 9 0 1 2 3 4 5 6 7 8 9 0 1 2 3 4 5 6 7 8 9 0 1
  +-+-+-+-+-+-+-+-+-+-+-+-+-+-+-+-+-+-+-+-+-+-+-+-+-+-+-+-+-+-+-+-+
  |             Type              |             Length            |
  +-+-+-+-+-+-+-+-+-+-+-+-+-+-+-+-+-+-+-+-+-+-+-+-+-+-+-+-+-+-+-+-+
  |        Reserved (MBZ)         |             Flags       |L|N|R|
  +-+-+-+-+-+-+-+-+-+-+-+-+-+-+-+-+-+-+-+-+-+-+-+-+-+-+-+-+-+-+-+-+
  |                 Opposite Direction Path ID                    |
  +-+-+-+-+-+-+-+-+-+-+-+-+-+-+-+-+-+-+-+-+-+-+-+-+-+-+-+-+-+-+-+-+

]]></artwork></figure>

<t>Type: TBD9 for “MULTIPATH-OPPDIR-PATH” TLV</t>

<t>Length: 16.</t>

<t>R (Reverse path): If set, indicates this path is reverse,
i.e., it
originates on the Tunnel destination and terminates on the
Tunnel source (usually the PCC headend itself).
Paths with this flag set MUST NOT
be installed into forwarding, they serve only informational
purposes.</t>

<t>N (Node co-routed): If set, indicates this path is
node co-routed with
its opposite direction path, specified in this TLV.
Two opposite direction paths are node co-routed if they
traverse the same nodes,
but MAY traverse different links.</t>

<t>L (Link co-routed): If set, indicates this path is
link co-routed with
its opposite directions path, specified in this TLV.
Two opposite direction paths are link co-routed if they
traverse the same links (but in the opposite directions).</t>

<t>Opposite Direction Path ID: Identifies the path that
goes in the opposite direction to this path.
If no such path exists, then this field MUST be set to 0x0,
which is reserved to indicate the absense of a Path ID.</t>

<t>Multiple copies of this TLV
present in the same PATH-ATTRIB object indicate that there are multiple
opposite-direction paths corresponding to the given path. This allows for
many-to-many relationship among the paths of two opposite direction Tunnels.</t>

<t>Whenever one path A references another path B as being the
opposite-direction path, then path B typically also reference path A as its
own opposite-direction path.</t>

<t>See <xref target="OPPDIREX"/> for an example of usage.</t>

</section>
<section anchor="CCP" title="Composite Candidate Path">

<t>SR Policy Architecture <xref target="I-D.ietf-spring-segment-routing-policy"/> defines the concept of a
Composite Candidate Path. Unlike a Non-Composite Candidate Path, which contains
Segment Lists, the Composite Candidate Path contains
Colors of other policies. The traffic that is steered into a Composite Candidate Path is
split among the policies that are identified by the Colors contained in
the Composite Candidate Path. The split can be either ECMP or UCMP by adjusting the
weight of each color in the Composite Candidate Path,
in the same manner as the weight of each
Segment List in the Non-Composite Candidate Path is adjusted.</t>

<t>To signal the Composite Candidate Path, we make use of the COLOR TLV, defined in
<xref target="I-D.peng-pce-te-constraints"/>. For a Composite Candidate Path, the COLOR TLV
is included in the PATH-ATTRIB Object, thus allowing each Composite Candidate Path
to do ECMP/UCMP among SR Policies or Tunnels identified by its constituent Colors.
Only one COLOR TLV SHOULD be included into the PATH-ATTRIB object. If multiple
COLOR TLVs are contained in the PATH-ATTRIB object, only the first one MUST be
processed and the others SHOULD be ignored.</t>

<t>An empty SR-ERO/SR-RRO object MUST be included as per the existing RBNF, i.e.,
SR-ERO/SR-RRO MUST contain no sub-objects.
If the head-end receives a non-empty SR-ERO/SR-RRO,
then it MUST send PCError message with Error-Type 19 (“Invalid Operation”) and
Error-Value = TBD8 (“Non-empty path”).</t>

<t>See <xref target="CCPEX"/> for an example of the encoding.</t>

</section>
</section>
<section anchor="OP" title="Operation">

<t>When the PCC wants to indicate to the PCE that it wants to get
multipaths for a PCEP Tunnel, instead of a single path, it can do (1) or both (1) and (2) of the
following:</t>

<t>(1) Send the MULTIPATH-CAP TLV in the OPEN object during session
       establishment.  This applies to all PCEP Tunnels on the PCC,
       unless overridden by PCEP Tunnel specific information.</t>

<t>(2) Additionally send the MULTIPATH-CAP TLV in the LSP object for a particular
       PCEP Tunnel in the PCRpt or PCReq message.  This applies to the specified
       PCEP Tunnel and overrides the information from the OPEN object.</t>

<t>When PCE computes the path for a PCEP Tunnel, it MUST NOT return more
multipaths than the corresponding value of “Number of Multipaths”
from the MULTIPATH-CAP TLV.  If this TLV is absent (from both OPEN
and LSP objects), then the “Number of Multipaths” is assumed to be 1.</t>

<t>If the PCE supports this standard, then it MUST include the
MULTIPATH-CAP TLV in the OPEN object.  This tells the PCC that it can
report multiple ERO/RRO objects per PCEP Tunnel to this PCE.  If the PCE does not include
the MULTIPATH-CAP TLV in the OPEN object, then the PCC MUST assume
that the PCE does not support this standard and fall back to
reporting only a single ERO/RRO. The PCE MUST NOT include MULTIPATH-CAP TLV
in the LSP object in any other PCEP message towards the PCC and the PCC MUST ignore it if received.</t>

<t>The Path ID of each ERO/RRO MUST be unique within that LSP.
If a PCEP speaker detects that there are two paths with the same Path ID,
then the PCEP speaker SHOULD send PCError message with
Error-Type = 1 (“Reception of an invalid object”) and
Error-Value = TBD5 (“Conflicting Path ID”).</t>

<section anchor="signaling-multiple-paths-for-loadbalancing" title="Signaling Multiple Paths for Loadbalancing">

<t>The PATH-ATTRIB object can be used to signal multiple path(s) and indicate
(un)equal loadbalancing amongst the set of multipaths. In this case, the
PATH-ATTRIB is populated for each ERO as follows:</t>

<t><list style="numbers">
  <t>The PCE assigns a unique Path ID to each ERO path and populates
it inside the PATH-ATTRIB object. The Path ID is unique within the
context of a PLSP or PCEP Tunnel.</t>
  <t>The MULTIPATH-WEIGHT TLV MAY be carried inside the PATH-ATTRIB object. A
weight is populated to reflect the relative loadshare that is to be
carried by the path. If the MULTIPATH-WEIGHT is not carried inside a
PATH-ATTRIB object, the default weight 1 MUST be assumed when computing
the loadshare.</t>
  <t>The fraction of flows carried by a specific primary path is derived
from the ratio of its weight to the sum of all other multipath weights.</t>
</list></t>

</section>
<section anchor="signaling-multiple-paths-for-protection" title="Signaling Multiple Paths for Protection">

<t>The PATH-ATTRIB object can be used to describe a set of backup path(s) protecting
a primary path within a PCEP Tunnel. In this case, the PATH-ATTRIB is populated for each ERO as
follows:</t>

<t><list style="numbers">
  <t>The PCE assigns a unique Path ID to each ERO path and populates
it inside the PATH-ATTRIB object. The Path ID is unique within the
context of a PLSP or PCEP Tunnel.</t>
  <t>The MULTIPATH-BACKUP TLV MUST be added inside the PATH-ATTRIB object for each
ERO that is protected. The backup path ID(s) are populated in the
MULTIPATH-BACKUP TLV to reflect the set of backup path(s) protecting the
primary path. The Length field and Backup Path Number in the MULTIPATH-BACKUP
are updated according to the number of backup path ID(s) included.</t>
  <t>The MULTIPATH-BACKUP TLV MAY be added inside the PATH-ATTRIB object for each
ERO that is unprotected. In this case, MULTIPATH-BACKUP does not carry
any backup path IDs in the TLV. If the path acts as a pure backup – i.e.
the path only carries rerouted traffic after the protected path(s) fail– then
the B flag MUST be set.</t>
</list></t>

<t>Note that if a given path has the B-flag set, then there MUST be some other path
within the same LSP that uses the given path as a backup.
If this condition is violated, then the PCEP speaker SHOULD send a PCError message
with Error-Type = 10 (“Reception of an invalid object”) and
Error-Value = TBD6 (“No primary path for pure backup”).</t>

<t>Note that a given PCC may not support certain backup combinations,
such as a backup path that is itself protected by another backup path, etc.
If a PCC is not able to implement a requested backup scenario,
the PCC SHOULD send a PCError message with
Error-Type = 19 (“Invalid Operation”) and
Error-Value = TBD7 (“Not supported path backup”).</t>

</section>
</section>
<section anchor="RBNF" title="PCEP Message Extensions">

<t>The RBNF of PCReq, PCRep, PCRpt, PCUpd and PCInit messages currently use a combination
of &lt;intended-path&gt; and/or &lt;actual-path&gt;.
As specified in Section 6.1 of <xref target="RFC8231"/>, &lt;intended-path&gt; is represented by the
ERO object and &lt;actual-path&gt; is represented by the RRO object:</t>

<figure><artwork><![CDATA[
   <intended-path> ::= <ERO>

   <actual-path> ::= <RRO>
]]></artwork></figure>

<t>In this standard, we extend these two elements to allow multiple ERO/RRO objects to be
present in the &lt;intended-path&gt;/&lt;actual-path&gt;:</t>

<figure><artwork><![CDATA[
   <intended-path> ::= (<ERO>|
                       (<PATH-ATTRIB><ERO>)
                       [<intended-path>])
              

   <actual-path> ::= (<RRO>|
                      (<PATH-ATTRIB><RRO>)
                      [<actual-path>])
]]></artwork></figure>

</section>
<section anchor="examples" title="Examples">

<section anchor="sr-policy-candidate-path-with-multiple-segment-lists" title="SR Policy Candidate-Path with Multiple Segment-Lists">

<t>Consider the following sample SR Policy, taken from<vspace />
<xref target="I-D.ietf-spring-segment-routing-policy"/>.</t>

<figure><artwork><![CDATA[
        SR policy POL1 <headend, color, endpoint>
            Candidate-path CP1 <protocol-origin = 20, originator =
    100:1.1.1.1, discriminator = 1>
                Preference 200
                Weight W1, SID-List1 <SID11...SID1i>
                Weight W2, SID-List2 <SID21...SID2j>
            Candidate-path CP2 <protocol-origin = 20, originator =
    100:2.2.2.2, discriminator = 2>
                Preference 100
                Weight W3, SID-List3 <SID31...SID3i>
                Weight W4, SID-List4 <SID41...SID4j>
]]></artwork></figure>

<t>As specified in <xref target="I-D.ietf-pce-segment-routing-policy-cp"/>, CP1 and CP2 
are signaled as separate state-report elements and each has 
a unique PLSP-ID, assigned by the PCC. 
Let us assign PLSP-ID 100 to CP1 and PLSP-ID 200 to CP2.</t>

<t>The state-report for CP1 can be encoded as:</t>

<figure><artwork><![CDATA[
<state-report> =
        <LSP PLSP_ID=100>
        <ASSOCIATION>
        <END-POINT>
        <PATH-ATTRIB Path_ID=1 <WEIGHT-TLV Weight=W1>>
        <ERO SID-List1>
        <PATH-ATTRIB Path_ID=2 <WEIGHT-TLV Weight=W2>>
        <ERO SID-List2>
]]></artwork></figure>

<t>The state-report for CP2 can be encoded as:</t>

<figure><artwork><![CDATA[
<state-report> =
        <LSP PLSP_ID=200>
        <ASSOCIATION>
        <END-POINT>
        <PATH-ATTRIB Path_ID=1 <WEIGHT-TLV Weight=W3>>
        <ERO SID-List3>
        <PATH-ATTRIB Path_ID=2 <WEIGHT-TLV Weight=W4>>
        <ERO SID-List4>
]]></artwork></figure>

<t>The above sample state-report elements only 
specify the minimum mandatory objects, 
of course other objects like SRP, LSPA, METRIC, etc., are allowed to be 
inserted.</t>

<t>Note that the syntax</t>

<figure><artwork><![CDATA[
<PATH-ATTRIB Path_ID=1 <WEIGHT-TLV Weight=W1>>
]]></artwork></figure>

<t>, simply means that this is PATH-ATTRIB object 
with Path ID field set to “1” and 
with a MULTIPATH-WEIGHT TLV carrying weight of “W1”.</t>

</section>
<section anchor="two-primary-paths-protected-by-one-backup-path" title="Two Primary Paths Protected by One Backup Path">

<t>Suppose there are 3 paths: A, B, C.
Where A,B are primary and C is to be used only when A or B fail.
Suppose the Path IDs for A, B, C are respectively 1, 2, 3.
This would be encoded in a state-report as:</t>

<figure><artwork><![CDATA[
<state-report> =
        <LSP>
        <ASSOCIATION>
        <END-POINT>
        <PATH-ATTRIB Path_ID=1 <BACKUP-TLV B=0, Backup_Paths=[3]>>
        <ERO A>
        <PATH-ATTRIB Path_ID=2 <BACKUP-TLV B=0, Backup_Paths=[3]>>
        <ERO B>
        <PATH-ATTRIB Path_ID=3 <BACKUP-TLV B=1, Backup_Paths=[]>>
        <ERO C>
]]></artwork></figure>

<t>Note that the syntax</t>

<figure><artwork><![CDATA[
<PATH-ATTRIB Path_ID=1 <BACKUP-TLV B=0, Backup_Paths=[3]>>
]]></artwork></figure>

<t>, simply means that this is PATH-ATTRIB object 
with Path ID field set to “1” and 
with a MULTIPATH-BACKUP TLV that has B-flag cleared and contains
a single backup path with Backup Path ID of 3.</t>

</section>
<section anchor="CCPEX" title="Composite Candidate Path">

<t>Consider the following Composite Candidate Path, taken from<vspace />
<xref target="I-D.ietf-spring-segment-routing-policy"/>.</t>

<figure><artwork><![CDATA[
   SR policy POL100 <headend = H1, color = 100, endpoint = E1>
        Candidate-path CP1 <protocol-origin = 20, originator =
   100:1.1.1.1, discriminator = 1>
            Preference 200
            Weight W1, SR policy <color = 1>
            Weight W2, SR policy <color = 2>
]]></artwork></figure>

<t>This is signaled in PCEP as:</t>

<figure><artwork><![CDATA[
    <LSP PLSP_ID=100>
        <ASSOCIATION>
        <END-POINT>
        <PATH-ATTRIB Path_ID=1
            <WEIGHT-TLV Weight=W1>
            <COLOR-TLV Color=1>>
        <SR-ERO (empty)>
        <PATH-ATTRIB Path_ID=2
            <WEIGHT-TLV Weight=W2>
            <COLOR-TLV Color=2>>
        <SR-ERO (empty)>
]]></artwork></figure>

</section>
<section anchor="OPPDIREX" title="Opposite Direction Tunnels">

<t>Consider the two opposite-direction SR Policies between
end-points H1 and E1.</t>

<figure><artwork><![CDATA[
    SR policy POL1 <headend = H1, color, endpoint = E1>
        Candidate-path CP1
            Preference 200
            Bidirectional Association = A1
            SID-List = <H1,M1,M2,E1>
            SID-List = <H1,M3,M4,E1>
        Candidate-path CP2
            Preference 100
            Bidirectional Association = A2
            SID-List = <H1,M5,M6,E1>
            SID-List = <H1,M7,M8,E1>

    SR policy POL2 <headend = E1, color, endpoint = H1>
        Candidate-path CP1
            Preference 200
            Bidirectional Association = A1
            SID-List = <E1,M2,M1,H1>
            SID-List = <E1,M4,M3,H1>
        Candidate-path CP2
            Preference 100
            Bidirectional Association = A2
            SID-List = <E1,M6,M5,H1>
]]></artwork></figure>

<t>The state-report for POL1, CP1 can be encoded as:</t>

<figure><artwork><![CDATA[
    <state-report> =
        <LSP PLSP_ID=100>
        <BIDIRECTIONAL ASSOCIATION = A1>
        <PATH-ATTRIB PathID=1
            <OPPDIR-PATH-TLV R-flag=0 OppositePathID=3>>
        <ERO <H1,M1,M2,E1>>
        <PATH-ATTRIB PathID=2
            <OPPDIR-PATH-TLV R-flag=0 OppositePathID=4>>
        <ERO <H1,M3,M4,E1>>
        <PATH-ATTRIB PathID=3
            <OPPDIR-PATH-TLV R-flag=1 OppositePathID=1>>
        <ERO <E1,M2,M1,H1>>
        <PATH-ATTRIB PathID=4
            <OPPDIR-PATH-TLV R-flag=1 OppositePathID=2>>
        <ERO <E1,M4,M3,H1>>
]]></artwork></figure>

<t>The state-report for POL1, CP2 can be encoded as:</t>

<figure><artwork><![CDATA[
    <state-report> =
        <LSP PLSP_ID=200>
        <BIDIRECTIONAL ASSOCIATION = A2>
        <PATH-ATTRIB PathID=1
            <OPPDIR-PATH-TLV R-flag=0 OppositePathID=3>>
        <ERO <H1,M5,N6,E1>>
        <PATH-ATTRIB PathID=2
            <OPPDIR-PATH-TLV R-flag=0 OppositePathID=0>>
        <ERO <H1,M7,M8,E1>>
        <PATH-ATTRIB PathID=3
            <OPPDIR-PATH-TLV R-flag=1 OppositePathID=1>>
        <ERO <E1,M6,M5,H1>>
]]></artwork></figure>

<t>The state-report for POL2, CP1 can be encoded as:</t>

<figure><artwork><![CDATA[
    <state-report> =
        <LSP PLSP_ID=100>
        <BIDIRECTIONAL ASSOCIATION = A1>
        <PATH-ATTRIB PathID=1
            <OPPDIR-PATH-TLV R-flag=0 OppositePathID=3>>
        <ERO <E1,M2,M1,H1>>
        <PATH-ATTRIB PathID=2
            <OPPDIR-PATH-TLV R-flag=0 OppositePathID=4>>
        <ERO <E1,M4,M3,H1>>
        <PATH-ATTRIB PathID=3
            <OPPDIR-PATH-TLV R-flag=1 OppositePathID=1>>
        <ERO <H1,M1,M2,E1>>
        <PATH-ATTRIB PathID=4
            <OPPDIR-PATH-TLV R-flag=1 OppositePathID=2>>
        <ERO <H1,M3,M4,E1>>
]]></artwork></figure>

<t>The state-report for POL2, CP2 can be encoded as:</t>

<figure><artwork><![CDATA[
    <state-report> =
        <LSP PLSP_ID=200>
        <BIDIRECTIONAL ASSOCIATION = A2>
        <PATH-ATTRIB PathID=1
            <OPPDIR-PATH-TLV R-flag=0 OppositePathID=3>>
        <ERO <E1,M6,M5,H1>>
        <PATH-ATTRIB PathID=2
            <OPPDIR-PATH-TLV R-flag=1 OppositePathID=0>>
        <ERO <H1,M7,M8,E1>>
        <PATH-ATTRIB PathID=3
            <OPPDIR-PATH-TLV R-flag=1 OppositePathID=1>>
        <ERO <H1,M5,N6,E1>>
]]></artwork></figure>

</section>
</section>
<section anchor="iana-considerations" title="IANA Considerations">

<section anchor="pcep-object" title="PCEP Object">
<t>IANA is requested to make the assignment of a new value for the
   existing “PCEP Objects” registry as follows:</t>

<figure><artwork><![CDATA[
 +--------------+-------------+-------------------+-----------------+
 | Object-Class | Name        | Object-Type       | Reference       |
 | Value        |             | Value             |                 |
 +--------------+-------------+-------------------+-----------------+
 | TBD2         | PATH-ATTRIB | 1                 | This document   |
 +--------------+-------------+-------------------+-----------------+
]]></artwork></figure>

</section>
<section anchor="pcep-tlv" title="PCEP TLV">
<t>IANA is requested to make the assignment of a new value for the
   existing “PCEP TLV Type Indicators” registry as follows:</t>

<figure><artwork><![CDATA[
 +------------+-----------------------------------+-----------------+
 | TLV Type   | TLV Name                          | Reference       |
 | Value      |                                   |                 |
 +------------+-----------------------------------+-----------------+
 | TBD1       | MULTIPATH-CAP                     | This document   |
 +------------+-----------------------------------+-----------------+
 | TBD3       | MULTIPATH-WEIGHT                  | This document   |
 +------------+-----------------------------------+-----------------+
 | TBD4       | MULTIPATH-BACKUP                  | This document   |
 +------------+-----------------------------------+-----------------+
 | TBD9       | MULTIPATH-OPPDIR-PATH             | This document   |
 +------------+-----------------------------------+-----------------+
]]></artwork></figure>

</section>
<section anchor="pcep-error-object" title="PCEP-Error Object">
<t>IANA is requested to make the assignment of a new value for the
   existing “PCEP-ERROR Object Error Types and Values” sub-registry of the
   PCEP Numbers registry for the following errors:</t>

<figure><artwork><![CDATA[
 +------------+-----------------------------------+-----------------+
 | Error-Type | Error-Value                       | Reference       |
 +------------+-----------------------------------+-----------------+
 | 10         | TBD5 - Conflicting Path ID        | This document   |
 +------------+-----------------------------------+-----------------+
 | 10         | TBD6 - No primary path for pure   | This document   |
 |            |        backup                     |                 |
 +------------+-----------------------------------+-----------------+
 | 19         | TBD7 - Not supported path backup  | This document   |
 +------------+-----------------------------------+-----------------+
 | 19         | TBD8 - Non-empty path             | This document   |
 +------------+-----------------------------------+-----------------+
]]></artwork></figure>

</section>
<section anchor="flags-in-the-multipath-capability-tlv" title="Flags in the Multipath Capability TLV">

<t>IANA is requested to create a new sub-registry to manage the Flag
field of the MULTIPATH-CAP TLV, called “Flags in MULTIPATH-CAP
TLV”.</t>

<figure><artwork><![CDATA[
 +------------+-----------------------------------+-----------------+
 | Bit        | Description                       | Reference       |
 +------------+-----------------------------------+-----------------+
 | 0-12       | Unassigned                        | This document   |
 +------------+-----------------------------------+-----------------+
 | 13         | 0-flag: support for processing    | This document   |
 |            | MULTIPATH-OPPDIR-PATH TLV         |                 |
 +------------+-----------------------------------+-----------------+
 | 14         | B-flag: support for processing    | This document   |
 |            | MULTIPATH-BACKUP TLV              |                 |
 +------------+-----------------------------------+-----------------+
 | 15         | W-flag: support for processing    | This document   |
 |            | MULTIPATH-WEIGHT TLV              |                 |
 +------------+-----------------------------------+-----------------+
]]></artwork></figure>

</section>
<section anchor="flags-in-the-path-attribute-object" title="Flags in the Path Attribute Object">

<t>IANA is requested to create a new sub-registry to manage the Flag
field of the PATH-ATTRIBUTE object,
called “Flags in PATH-ATTRIBUTE Object”.</t>

<figure><artwork><![CDATA[
 +------------+-----------------------------------+-----------------+
 | Bit        | Description                       | Reference       |
 +------------+-----------------------------------+-----------------+
 | 0-12       | Unassigned                        | This document   |
 +------------+-----------------------------------+-----------------+
 | 13-15      | O-flag: Operational state         | This document   |
 +------------+-----------------------------------+-----------------+
]]></artwork></figure>

</section>
<section anchor="flags-in-the-multipath-backup-tlv" title="Flags in the Multipath Backup TLV">

<t>IANA is requested to create a new sub-registry to manage the Flag
field of the MULTIPATH-BACKUP TLV,
called “Flags in MULTIPATH-BACKUP TLV”.</t>

<figure><artwork><![CDATA[
 +------------+-----------------------------------+-----------------+
 | Bit        | Description                       | Reference       |
 +------------+-----------------------------------+-----------------+
 | 0-14       | Unassigned                        | This document   |
 +------------+-----------------------------------+-----------------+
 | 15         | B-flag: Pure backup               | This document   |
 +------------+-----------------------------------+-----------------+
]]></artwork></figure>

</section>
<section anchor="flags-in-the-multipath-opposite-direction-path-tlv" title="Flags in the Multipath Opposite Direction Path TLV">

<t>IANA is requested to create a new sub-registry to manage the flag
fields of the MULTIPATH-OPPDIR-PATH TLV,
called “Flags in the MULTIPATH-OPPDIR-PATH TLV”.</t>

<figure><artwork><![CDATA[
 +------------+-----------------------------------+-----------------+
 | Bit        | Description                       | Reference       |
 +------------+-----------------------------------+-----------------+
 | 0-12       | Unassigned                        | This document   |
 +------------+-----------------------------------+-----------------+
 | 13         | L-flag: Link co-routed            | This document   |
 +------------+-----------------------------------+-----------------+
 | 14         | N-flag: Node co-routed            | This document   |
 +------------+-----------------------------------+-----------------+
 | 15         | R-flag: Reverse path              | This document   |
 +------------+-----------------------------------+-----------------+
]]></artwork></figure>

</section>
</section>
<section anchor="security-considerations" title="Security Considerations">

<t>None at this time.</t>

</section>
<section anchor="acknowledgement" title="Acknowledgement">

<t>Thanks to Dhruv Dhody for ideas and discussion.</t>

</section>
<section anchor="contributors" title="Contributors">

<figure><artwork><![CDATA[
   Andrew Stone
   Nokia

   Email: andrew.stone@nokia.com
]]></artwork></figure>

</section>


  </middle>

  <back>

    <references title='Normative References'>





<reference anchor='RFC2119' target='https://www.rfc-editor.org/info/rfc2119'>
<front>
<title>Key words for use in RFCs to Indicate Requirement Levels</title>
<author fullname='S. Bradner' initials='S.' surname='Bradner'><organization/></author>
<date month='March' year='1997'/>
<abstract><t>In many standards track documents several words are used to signify the requirements in the specification.  These words are often capitalized. This document defines these words as they should be interpreted in IETF documents.  This document specifies an Internet Best Current Practices for the Internet Community, and requests discussion and suggestions for improvements.</t></abstract>
</front>
<seriesInfo name='BCP' value='14'/>
<seriesInfo name='RFC' value='2119'/>
<seriesInfo name='DOI' value='10.17487/RFC2119'/>
</reference>



<reference anchor='RFC5440' target='https://www.rfc-editor.org/info/rfc5440'>
<front>
<title>Path Computation Element (PCE) Communication Protocol (PCEP)</title>
<author fullname='JP. Vasseur' initials='JP.' role='editor' surname='Vasseur'><organization/></author>
<author fullname='JL. Le Roux' initials='JL.' role='editor' surname='Le Roux'><organization/></author>
<date month='March' year='2009'/>
<abstract><t>This document specifies the Path Computation Element (PCE) Communication Protocol (PCEP) for communications between a Path Computation Client (PCC) and a PCE, or between two PCEs.  Such interactions include path computation requests and path computation replies as well as notifications of specific states related to the use of a PCE in the context of Multiprotocol Label Switching (MPLS) and Generalized MPLS (GMPLS) Traffic Engineering.  PCEP is designed to be flexible and extensible so as to easily allow for the addition of further messages and objects, should further requirements be expressed in the future.  [STANDARDS-TRACK]</t></abstract>
</front>
<seriesInfo name='RFC' value='5440'/>
<seriesInfo name='DOI' value='10.17487/RFC5440'/>
</reference>



<reference anchor='RFC8231' target='https://www.rfc-editor.org/info/rfc8231'>
<front>
<title>Path Computation Element Communication Protocol (PCEP) Extensions for Stateful PCE</title>
<author fullname='E. Crabbe' initials='E.' surname='Crabbe'><organization/></author>
<author fullname='I. Minei' initials='I.' surname='Minei'><organization/></author>
<author fullname='J. Medved' initials='J.' surname='Medved'><organization/></author>
<author fullname='R. Varga' initials='R.' surname='Varga'><organization/></author>
<date month='September' year='2017'/>
<abstract><t>The Path Computation Element Communication Protocol (PCEP) provides mechanisms for Path Computation Elements (PCEs) to perform path computations in response to Path Computation Client (PCC) requests.</t><t>Although PCEP explicitly makes no assumptions regarding the information available to the PCE, it also makes no provisions for PCE control of timing and sequence of path computations within and across PCEP sessions.  This document describes a set of extensions to PCEP to enable stateful control of MPLS-TE and GMPLS Label Switched Paths (LSPs) via PCEP.</t></abstract>
</front>
<seriesInfo name='RFC' value='8231'/>
<seriesInfo name='DOI' value='10.17487/RFC8231'/>
</reference>



<reference anchor='RFC8281' target='https://www.rfc-editor.org/info/rfc8281'>
<front>
<title>Path Computation Element Communication Protocol (PCEP) Extensions for PCE-Initiated LSP Setup in a Stateful PCE Model</title>
<author fullname='E. Crabbe' initials='E.' surname='Crabbe'><organization/></author>
<author fullname='I. Minei' initials='I.' surname='Minei'><organization/></author>
<author fullname='S. Sivabalan' initials='S.' surname='Sivabalan'><organization/></author>
<author fullname='R. Varga' initials='R.' surname='Varga'><organization/></author>
<date month='December' year='2017'/>
<abstract><t>The Path Computation Element Communication Protocol (PCEP) provides mechanisms for Path Computation Elements (PCEs) to perform path computations in response to Path Computation Client (PCC) requests.</t><t>The extensions for stateful PCE provide active control of Multiprotocol Label Switching (MPLS) Traffic Engineering Label Switched Paths (TE LSPs) via PCEP, for a model where the PCC delegates control over one or more locally configured LSPs to the PCE.  This document describes the creation and deletion of PCE-initiated LSPs under the stateful PCE model.</t></abstract>
</front>
<seriesInfo name='RFC' value='8281'/>
<seriesInfo name='DOI' value='10.17487/RFC8281'/>
</reference>



<reference anchor='RFC8664' target='https://www.rfc-editor.org/info/rfc8664'>
<front>
<title>Path Computation Element Communication Protocol (PCEP) Extensions for Segment Routing</title>
<author fullname='S. Sivabalan' initials='S.' surname='Sivabalan'><organization/></author>
<author fullname='C. Filsfils' initials='C.' surname='Filsfils'><organization/></author>
<author fullname='J. Tantsura' initials='J.' surname='Tantsura'><organization/></author>
<author fullname='W. Henderickx' initials='W.' surname='Henderickx'><organization/></author>
<author fullname='J. Hardwick' initials='J.' surname='Hardwick'><organization/></author>
<date month='December' year='2019'/>
<abstract><t>Segment Routing (SR) enables any head-end node to select any path without relying on a hop-by-hop signaling technique (e.g., LDP or RSVP-TE). It depends only on &quot;segments&quot; that are advertised by link-state Interior Gateway Protocols (IGPs). An SR path can be derived from a variety of mechanisms, including an IGP Shortest Path Tree (SPT), an explicit configuration, or a Path Computation Element (PCE). This document specifies extensions to the Path Computation Element Communication Protocol (PCEP) that allow a stateful PCE to compute and initiate Traffic-Engineering (TE) paths, as well as a Path Computation Client (PCC) to request a path subject to certain constraints and optimization criteria in SR networks.</t><t>This document updates RFC 8408.</t></abstract>
</front>
<seriesInfo name='RFC' value='8664'/>
<seriesInfo name='DOI' value='10.17487/RFC8664'/>
</reference>


<reference anchor='I-D.ietf-spring-segment-routing-policy'>
   <front>
      <title>Segment Routing Policy Architecture</title>
      <author fullname='Clarence Filsfils'>
	 <organization>Cisco Systems</organization>
      </author>
      <author fullname='Ketan Talaulikar'>
	 <organization>Cisco Systems</organization>
      </author>
      <author fullname='Daniel Voyer'>
	 <organization>Bell Canada</organization>
      </author>
      <author fullname='Alex Bogdanov'>
	 <organization>Google, Inc.</organization>
      </author>
      <author fullname='Paul Mattes'>
	 <organization>Microsoft</organization>
      </author>
      <date day='28' month='May' year='2021'/>
      <abstract>
	 <t>   Segment Routing (SR) allows a headend node to steer a packet flow
   along any path.  Intermediate per-path states are eliminated thanks
   to source routing.  The headend node steers a flow into an SR Policy.
   The packets steered into an SR Policy carry an ordered list of
   segments associated with that SR Policy.  This document details the
   concepts of SR Policy and steering into an SR Policy.

	 </t>
      </abstract>
   </front>
   <seriesInfo name='Internet-Draft' value='draft-ietf-spring-segment-routing-policy-13'/>
   <format target='https://www.ietf.org/archive/id/draft-ietf-spring-segment-routing-policy-13.txt' type='TXT'/>
</reference>


<reference anchor='I-D.ietf-pce-segment-routing-policy-cp'>
   <front>
      <title>PCEP extension to support Segment Routing Policy Candidate Paths</title>
      <author fullname='Mike Koldychev'>
	 <organization>Cisco Systems, Inc.</organization>
      </author>
      <author fullname='Siva Sivabalan'>
	 <organization>Ciena Corporation</organization>
      </author>
      <author fullname='Colby Barth'>
	 <organization>Juniper Networks, Inc.</organization>
      </author>
      <author fullname='Shuping Peng'>
	 <organization>Huawei Technologies</organization>
      </author>
      <author fullname='Hooman Bidgoli'>
	 <organization>Nokia</organization>
      </author>
      <date day='23' month='May' year='2021'/>
      <abstract>
	 <t>   This document introduces a mechanism to specify a Segment Routing
   (SR) policy, as a collection of SR candidate paths.  An SR policy is
   identified by &lt;headend, color, endpoint&gt; tuple.  An SR policy can
   contain one or more candidate paths where each candidate path is
   identified in PCEP by its uniquely assigned PLSP-ID.  This document
   proposes extension to PCEP to support association among candidate
   paths of a given SR policy.  The mechanism proposed in this document
   is applicable to both MPLS and IPv6 data planes of SR.


	 </t>
      </abstract>
   </front>
   <seriesInfo name='Internet-Draft' value='draft-ietf-pce-segment-routing-policy-cp-05'/>
   <format target='https://www.ietf.org/archive/id/draft-ietf-pce-segment-routing-policy-cp-05.txt' type='TXT'/>
</reference>



<reference anchor='RFC8174' target='https://www.rfc-editor.org/info/rfc8174'>
<front>
<title>Ambiguity of Uppercase vs Lowercase in RFC 2119 Key Words</title>
<author fullname='B. Leiba' initials='B.' surname='Leiba'><organization/></author>
<date month='May' year='2017'/>
<abstract><t>RFC 2119 specifies common key words that may be used in protocol  specifications.  This document aims to reduce the ambiguity by clarifying that only UPPERCASE usage of the key words have the  defined special meanings.</t></abstract>
</front>
<seriesInfo name='BCP' value='14'/>
<seriesInfo name='RFC' value='8174'/>
<seriesInfo name='DOI' value='10.17487/RFC8174'/>
</reference>


<reference anchor='I-D.koldychev-pce-operational'>
   <front>
      <title>PCEP Operational Clarification</title>
      <author fullname='Mike Koldychev'>
	 <organization>Cisco Systems, Inc.</organization>
      </author>
      <author fullname='Siva Sivabalan'>
	 <organization>Ciena Corporation</organization>
      </author>
      <author fullname='Shuping Peng'>
	 <organization>Huawei Technologies</organization>
      </author>
      <author fullname='Diego Achaval'>
	 <organization>Nokia</organization>
      </author>
      <author fullname='Hari Kotni'>
	 <organization>Juniper Networks, Inc</organization>
      </author>
      <date day='19' month='February' year='2021'/>
      <abstract>
	 <t>   This document is meant to provide better clarity about how PCEP
   operates and hence to facilitate better interoperability between
   different equipment vendors.  The content of this document has been
   compiled based on the feedback from several multi-vendor interop
   exercises.  Several constructs are introduced to facilitate this,
   such as the LSP-DB and the ASSO-DB.


	 </t>
      </abstract>
   </front>
   <seriesInfo name='Internet-Draft' value='draft-koldychev-pce-operational-03'/>
   <format target='https://www.ietf.org/archive/id/draft-koldychev-pce-operational-03.txt' type='TXT'/>
</reference>


<reference anchor='I-D.peng-pce-te-constraints'>
   <front>
      <title>PCE TE Constraints</title>
      <author fullname='Shaofu Peng'>
	 <organization>ZTE Corporation</organization>
      </author>
      <author fullname='Quan Xiong'>
	 <organization>ZTE Corporation</organization>
      </author>
      <author fullname='Fengwei Qin'>
	 <organization>China Mobile</organization>
      </author>
      <author fullname='Mike Koldychev'>
	 <organization>Cisco Systems</organization>
      </author>
      <author fullname='Siva Sivabalan'>
	 <organization>Ciena Corporation</organization>
      </author>
      <date day='11' month='July' year='2021'/>
      <abstract>
	 <t>   This document proposes a set of extensions for PCEP to support the TE
   constraints during path computation, e.g, IGP instance, virtual
   network, Slice-id, specific application, color template and FA-id
   etc.

	 </t>
      </abstract>
   </front>
   <seriesInfo name='Internet-Draft' value='draft-peng-pce-te-constraints-06'/>
   <format target='https://www.ietf.org/archive/id/draft-peng-pce-te-constraints-06.txt' type='TXT'/>
</reference>




    </references>

    <references title='Informative References'>





<reference anchor='RFC8745' target='https://www.rfc-editor.org/info/rfc8745'>
<front>
<title>Path Computation Element Communication Protocol (PCEP) Extensions for Associating Working and Protection Label Switched Paths (LSPs) with Stateful PCE</title>
<author fullname='H. Ananthakrishnan' initials='H.' surname='Ananthakrishnan'><organization/></author>
<author fullname='S. Sivabalan' initials='S.' surname='Sivabalan'><organization/></author>
<author fullname='C. Barth' initials='C.' surname='Barth'><organization/></author>
<author fullname='I. Minei' initials='I.' surname='Minei'><organization/></author>
<author fullname='M. Negi' initials='M.' surname='Negi'><organization/></author>
<date month='March' year='2020'/>
<abstract><t>An active stateful Path Computation Element (PCE) is capable of computing as well as controlling via Path Computation Element Communication Protocol (PCEP) Multiprotocol Label Switching Traffic Engineering (MPLS-TE) Label Switched Paths (LSPs). Furthermore, it is also possible for an active stateful PCE to create, maintain, and delete LSPs. This document defines the PCEP extension to associate two or more LSPs to provide end-to-end path protection.</t></abstract>
</front>
<seriesInfo name='RFC' value='8745'/>
<seriesInfo name='DOI' value='10.17487/RFC8745'/>
</reference>



<reference anchor='RFC4655' target='https://www.rfc-editor.org/info/rfc4655'>
<front>
<title>A Path Computation Element (PCE)-Based Architecture</title>
<author fullname='A. Farrel' initials='A.' surname='Farrel'><organization/></author>
<author fullname='J.-P. Vasseur' initials='J.-P.' surname='Vasseur'><organization/></author>
<author fullname='J. Ash' initials='J.' surname='Ash'><organization/></author>
<date month='August' year='2006'/>
<abstract><t>Constraint-based path computation is a fundamental building block for traffic engineering systems such as Multiprotocol Label Switching (MPLS) and Generalized Multiprotocol Label Switching (GMPLS) networks.  Path computation in large, multi-domain, multi-region, or multi-layer networks is complex and may require special computational components and cooperation between the different network domains.</t><t>This document specifies the architecture for a Path Computation Element (PCE)-based model to address this problem space.  This document does not attempt to provide a detailed description of all the architectural components, but rather it describes a set of building blocks for the PCE architecture from which solutions may be constructed.  This memo provides information for the Internet community.</t></abstract>
</front>
<seriesInfo name='RFC' value='4655'/>
<seriesInfo name='DOI' value='10.17487/RFC4655'/>
</reference>




    </references>



  </back>

<!-- ##markdown-source:
H4sIAF8BAGEAA+09a3MbN5Lf8StwyhfpQjIiJTuOyvaFophYt3rwKDnevezW
1pAEpYmHM9zBUArXdn779QPAYF6UFEveq9TSqYiaAdCNRr/RgNrttsjCLFIH
cjQYjuTw10zFOkxiLedJKi/CqziIwvhKnq6iLFwG2bU8juHNIsigkQgmk1Td
1Pd1PcQsmcbBAkDM0mCetUOVzdvLqWovbIv27q6YBpm6StL1gdTZTITL9EBm
6Upnvd3d73Z7IkhVcCDHySpDbMRtkr6/SpPVkmDLd/ArPv8RH0khdBbEs78H
URID1LXSYhkeyJ+zZNqSOkmzVM01fFsv8MvfhAhW2XWSHgjZFhI+YawP5GlH
/imJZuvptbqhpzyF0/C9Kr1I0qsgDv9JFDmQg1BPE3mx1plaAJDjeNqhVmoR
hNGBXLznvt9PsV1nmiwKUC86QPObYBJEQexBxWelF2WoKg7kIEmXScpL48HU
mnsCTGhVgXkJMINg5oG7BGq/zx8WQf33Kg6XKpVnKsNVqJljpqHn979wu06s
sgK4nzryUKk0WHgAfwr1dbySo+AmiP23D4V8M6G+jbDfAOxwdpVEoQf8TZIs
EKz3ogj3LHkfBj6Ya+rRmXCP72N8XyHrYUf+JZgFPvMcXq+WKgYp8N7UrKMP
arLGlg0rB9wyUvGVzygAAQXBPS4O/2YV3KpQXqrpdZxEyVUIouEBA+SuNI/w
/TU1JZDwiVnkbxQIiRz/MOh1u98dCBFaXeBevPh2/xm8aLfbMpjoLA2mmRCD
VZqqOGM1QbIZpDMtgyhKbmUSR2v4n4Ipgf6YqZmE99+AAoGuqyCSpHSyRE6U
XKZKwzgAVgY8WKqA4TOYpVwtZ6BBOrK/XEbhlOarZXYdZNDmH6swVdKpG6lX
S+qmV9NrGWhxMZYjWMjp2rUFflBWnSFwRlU7dchjRRWkhYe0lrdhdk24augD
jQnlhdI6uAJML69DLUE3rhZIGxgoTWarqdIGrVg4DDpyGE+TGQJO5o2wZQE2
jQ1UnayFsp1dz+GvSKQwI4Wq5PnkFzXNtNwejs/1jh3OtR6raZLOuK1wbcfY
Fugt9VJNQ4Cr1TIA5QM9E2pDKKh5GAOGQIXMn24LiCrmwTSMwgyWjV4aiiyA
OYFl9QL7B7yaE8ACVuFi3L4cInpyfPHTyH4PtYClD5agGWHhruJEZyGoBeLB
RTibRUqIr0BVMH1JOYoRssEgWSxXGbGKHEaKlmEb1mgH3yxAhTAbyVGagOlI
Ino52hEfPvwHcPqz/f3dT58kyCVgh6ym5LTQbQJqSili1TK0QRQiH8N4AyJ3
3gaxjIrYtJC97WCg+ZCNtJwEGugKc0HAaAODdHodZkD3FfDvhw//BSjuP3/2
7NMnIEWdfcZ+F0j8+SqiAU6TmYokT+5Fb68Lk5spPU3DCUwPeBh0KXCfykfJ
EuZokjKmA/IgKAOgBE8EOrAfYEl4EkxUJC5AMgBbYMlLcAnm4RQY/AoYRaX4
bPt0dHIBq8uk+VHFoNOj8J8wXXwht3/EHzsiW8WxioBtHM4vijjjDAFr8Ahw
nEyB0kluY8QJ0G6HcZiFMP2ZOLkYabkCSWKimClonzYLpE2LBBqkgJoBtjMi
ZJRMg0jAjOfh1Yqtr0StQesyAE6/Xhldh5PDHrM1aGuY9BTW2ExNeBQLYGyy
cA0rd6GuiDusN2Sm//z5/qdPgqRxDoq9tFKEThPXlzmcVpR1XlAkBIw0pQEU
y54hYt06im1cQtJGLdCy8lZFEf7EKaD6HuBgqHCVBmDSaGZWHQhGpVkQxkgY
tCOg7LZZN8lkmYULY9MkrHUG4AJUMaDHDeU0kK5MJqPiEXwdtkDF4/ZRh7xT
vcRHbc0jtFMeob2kEYjHALXICn08VUvQiLByF2NhoJBQL4HtA/ATaQHAIWT2
zgxwmFGChsZZH+Dk41iAEgX9tYqCtCVBQxfZGdpOYegQbV2bKBagbMLSRWrK
nDdHYypQfyegCAwR2iehzlBULhHjenNMhpgXHWgkcmPHQxaGkuiHDRwmyFgw
OA3o201hLW3DWrgRiDV1YQ0wQqhfgPZ0CWtgGB1kD9G+ScIZ2AE0Nzj+NUwC
aU5z8Cx/mAcvLVojYm7jKKARErchcCn4Gp7lCuIEaJ864wW8VbTd3JZXyHgQ
s4L45eJEOslSVjhrXsJN3oTs4HTQdF2qdBGSv7ZGyEq+V2sJXA5rtnX69uJy
q8U/5dk5fR8P/+ft8Xh4hN8v3vRPTtwXYVpcvDl/e3KUf8t7Ds5PT4dnR9wZ
nsrCI7F12v/LFlNu63x0eXx+1j/Zqlh3sEXKuGzoo6Tgt2XopuACMTcTXQ8H
I9ndN+oLPUpYVaPLut+CLpO318osE/Em/4oGb42yBfqcVgfWaxoswY+IWM/o
a9TysGAKqcfk0zRKn8LVkJ1DJuU8sYo542aA+UrXeCwHRhdfktWB316TLFlX
ZwZNUO3OwOFiXQtWpX18BGGmQnNMfP3exo3E3AnIEKESRDDXuZVYo1to5U8T
MEUczzHL5cKFnhK/zWEC4u0p+AVa5nQGc5vcMiHK0XxUUg9ke0gfFSWbKVV8
lrc1ohwy+4P7k+E7dsy/Ya8ciYnEI2I8RMhBpwxBgZZhgwokewlGIfdSi1PB
5VbYtaC1kILoDBPJBCo18HgByJvkVt0oULjUhdYZlg/hSAuHtaMwnjx0k9vm
VcGzBhcV34EdY84A7+32OoRBQQZuAA9wNMACpslCVr1yi6rgKZjogTQGBHfV
dYFVfRdicAQtrlW0RLrjd+dseSqo0REX9GsEBtX4BPBbArQAK2/k5wJc8Cwz
hmDM9hpGOgRcbsMZskefrPkiWJfNOU5BvtiVP06WxF0T26clJytSiQA5fq8Z
LSWM9ZbXAThgRPFnpjNIOEQL2dqYMHRFcHVAsaxS9oqNo0G6FhkkS64Uqe1p
kKZri0XHdB9Qd3gPgd4/VmRDMIiM7S8aJ03UDGGdFqisvXlYEx4sEtQc0Mph
0AFhfzc8/vHNZfvy5CcQbC+wC2CCtxIeWyzTNDRmg8mlwqvrzDMX7CzNgB1A
mFfWvjuMLBoco+IwjpcYF1o/cO5uQuK0w2D6HrxhgoUDo9unTER0bOI1Habk
yNsQocbpM1bVOpVAywBW1g3N3mOoWY9CqyWDQaZIw0UAi+GYw/C3M4LECYG8
Agc8RhHsSCHOEgoQYUyOajDF4Oz/Onds89mAFdDJlPW8WSP08XntASskYmEs
4lPPEsMir0iN6SloaZargn2jsJNoNF9RwKWz1WyN2L5DlioMhWRoFUlEsmLJ
gmrIKn9DIGFYSf5AqwCDpCrQ6LNYCiIG/oDOAKVswzA6IeqLEFQGJleNHvI6
oT9tkbBKKl8feNsBXX3YH/zp7aiGl2UjLzsXyPNogBXFV3mckUc0xKJ5dnkA
cj7BrMAaxwZyWk+MRj59e3J5POpfvmkP+qMcODglXnrIKBN5PhqeCWOfTUoD
H6Ni56dGlyxX6TLR+SrjsGjNbpM2eAczMPVSyi4uBqptYPcD9MsziGY0+ZmL
IF77HIyusecqtJyUoMYJIZhBtRdyhhY+QKJb8L9BPjsEqZdDGnqQjIfKAmnc
as0IWxeemAIwsiPfE7GhsXMk4IDDOepdfDUPU7SZiDGEOAX6YA+ieAK8QPwN
Fk+j8qf0HPfQ0niX6AdexcDfM5SQDx/ORyX5XWFGrACAJPJ8ibLE+TK57ekL
XFqziCYkJE3v59d0oUO+6MDU4rfffkMa7crqp1vzrFfzbI8H6MLLPbkvn8nn
8lv5Qn73kGcwxNftz/wHY3wsIHa5BoVV+BTfn6j4Ckjrv39UPM5WiwkshUv8
EOdV8fghCq60w+D84+HHd4+DB67thwP51Ty88jaYwH2QtM/1aquqQ1hJbX0C
PxeIdyAvD4+6pNuLbbewMXAPU/BA7sP3utkesEkLfg0Xq4WMXYs6SRQsimyZ
boJopYAxrMbGpBQ5ZqBKeRj0+NpzIN0BBkPE8zmKudeB6suoCBA5IQ4b++Ta
vdznvLHP+Wh0dDxu0/eajqDO2R73M/ZaYB6cNC5rcxqhf3k5Pj60cVTZdWDf
DchFyQ7hh8iU00swW8c5kDz9bHOlGn16cFTAIf9mDE45w9DC6IS/vrQJdBr8
r6+/+etLTqGb3+X48OwHqThH1qEgqAblILoN1hqNzxRMLltAC5Gnk3Eam9JA
mOOZizwRX0SNTLcxYy3jnWJEUmwmKdifKGFgUvwHCrmJnnkKKeTcRXEevDjt
QQRek+FBVMKHR73mxqRlXNvuH1ynNiqumg/0PH9snVr3IRE7PtqACWHzSHj8
1gzifMk5DNSOjYT57dF1O6n1gFSM1ew1/J+rdojXz/OEi2wD60zCTO8cSC8P
w+lAF0cHGKhS7C2I1zVqGooJydvm1CNuvM7AV1LRTFa8jcJ2SsfsOx0fgfFo
J9NMeYmj1CgL+7u2MbRNASgMSEQpwJMQtq3iEPwuwKTad9tmO8wgwiiSnUJy
gUYuhY7efohNh3TkObqBgaToROIuHbhZLRMJWH7ETTuNESIag5/Yov26KymE
0Sq9Yb3ughLacAHPMWYHPLDjoOpBfiKiYLREucRptPJmU6eMKYHm5Rgxq5Dn
+DTHhxhZnZNVSwrMO01W0cxP/oJe5fhO2NBPu7ymwcUjZA0+kwSiQraJeYzz
jsN8tJ0fvvJyBc3RDje6I+ARVfh/cL38r/Z1mz5mgTd8ntLXrdGMtZxU4/bu
ld1ebl7n+fIcD2zOysZujZmdlgzn8l17ODgd0Y49JpowHqQkPJaJmOTWnNJe
gdvecb6PzTBQlioNQZEIyqNSxgH1N6XGMG9qsmicntLgg6NigZibg8Q8N2NH
5g6YLaPkTaPooWqbkMA5wFWRawmbOKtqg+oA4k4n1LiBOOI7j9S475iC+C+T
GFMHwiabsuC9io2O2upuVXSPSQGy7vFyO+UtrUqmpxwz5MoIs2VWjaJTjsnX
ajamVjldevkW6/IXTAMPMjW2wU94GdCCuiHXLvP0H4DEbRBipyCMMD/nUuN5
gsvwHkkBmtbiunuzDPXBv/Xo0+pRw5amQGEVZ7V4lH3vj4dPr899zMC9qVvr
J6DHnXjU8dcXwYM+nU5nc4MvTo/4KfFoMLRGHVVsrKc6amzsftnGcvMtznc7
Eyu/lttn8j/l/o7cvsXNbHlm91grwrIjROXZgZeJK+b8MSF0II/n6Pi3vGRT
gJlw5Tc2FXmhiydI6eK+nLDWOFW4bYua226JzTMTNxiFDO94w4l2tREuOQqY
XRLwM04yRgSIEs7lBiVsbCfuWBqDaI0eBByrBVuPSa7jEVmHJxWwRhbLTpFg
x0fbGAhiDokaA8mq8RnulvghGmWuRWk7xQupqK3dXmHfyDc+QpYs8/lymegQ
7N4ROEZsxwg5NtWlpNtD7LXXtdZoC2O0a7ZQHm60bboQe/Munlsku9PBT7AI
TOCeeKqVC3TRfSvsUHhlYzhaoUYmmJhSPJEY0rVnjnR2QYzdz1H5d0j01CHR
2Mb526eH/7vTgIdvyj+efDz7OH46k9EkWfXZsyc1GcCpwKNVk1GW0Rq78V3Z
bnh9Ssaj+xy4fCy3x5547dSp/Dxko/wMtW6JsKM6WHsIkUx4FcbU0hS0slxi
iiXDFy4PTxVqXkOzryF1skrBe99eaS6rsFuh1yoALTpDgVfRHEzSyBXM5+aB
1KgtbBOUdKHNU8rsgNLJd04pSFpL4juuG/EUBWg4s8WLId4ZmNVkhuFTmy3X
nYQRcaE9ISlQU1m1I4tqp2VjV6/chuLny9ukqY/ZtC8CYnO4xjIPXkdXCoQN
dUtgDQ2mglyDWTifK6rtpLIaDNnl9gl8fch0o0L7TdPVnznfEqTm+XKR0DbO
11imGmTQsWkWdZh2nh51zgP5CFeJ0s3jciLB0KcjgHhxwkc0aAT1KxZruSgd
WZdSwWaPhl2BBHOgLcFFFr8jFerq9abJ0jgolsyiZLKJXnW5hxwMFxLgKZc0
rxhqMqK6mGiwaRXPoLKTmNcrCaw7aGdJm+oPUhVxveV1uPTqpXhonEc9k1ya
4n7OyaBmojoZInkfBiU2J2/HFOdydgMdhYkKGUjTlMximR7ZemmLiCOd5ENb
WAFum2lBJwfqx6NacyzyZI08/LMp56RDRMEC1w0mSjUOJh+DNfg842IFNDh6
g8EItH5eV9kvHut4SI16XpRsatSJrUQT8I58G0d4vDGQZ0ncbmpmCxpN9aN2
dfYnThCa5+c6DZIoSYkBzPIh2sDanJSxwYR1Val23qr9oHl40F5cuOcxmhnY
VNWlqqZW1yBjkCM4YtM0GEmGZBxnFdI0KL0JS/8Wf+Ku7OyXlc4sP+a5UtrV
nSJYK7eN5Ba+YINIxQDGbEMVxysshB1200qSV04I0sb9pauX34gPQAU03rtC
Omp8fnI+Rm3U8gpNbaEvniqkQl8QnPwwh8bq3h/oKEgzqMLYGC1u2gLireny
eRuidBMEAew0S2jVvqElY76x0keqNrW6qMQ4aBJpOmGGVU+GiTpcPoW6yiHu
l0Hl+NvyyWqIhQbaqWU3CptMn0ebMtDsAeUVXIhMXjJgKrbYb0OLh4xbV6ol
RB8U2GKZrU1V8zfwo1qFkM8p4MIWHJSsIpIfSyjA00CPUhRHoe62uppM6qRt
yiDIynJVczBro5+IhQ5gcSi4BY6uwcqkBUKDl8ZeEEqmKZZWmhIyci/pERcw
dL+T21vH8U0QhTPpdoe3qKRMcDvewXyFDvgLaHzmgKPi39pxqh/UdoPeJ3KY
Wm+ugsxBUWD/ydt3QN/4NjDbjLnJtpW2Q1dR4hpdqUx4lUX2cJUXQ6PXDHRk
n8LUr5sdGVZfIAHb3R06ZZjgpnGXa+q2ezZ8zndQuRgSW1wowz/VeqpqkZ6c
rVLef9XaHk6HD0QRwSQK9TUV2EjjSLhaGdq08aai/WN1doxVHMGgVLKehjOQ
UJRNr1O+kVSsRsVpwAT7s1nIQQIWfd85J29nnymdn9ayCPmwrYwOxks6pAxf
1D/yE8CVCZOet8503YBU68hTNabdz4i4bSmP9DxVKZnHqNqTKz09L7iOafLI
yxbZY4Gyz2rAinF1J8pUBQHjbNUVx23lm3YVIlNtlPRrcM1u2Tb1Ieakol6k
Qr4SesfbI6sHWk0SYsmSUTLNBbVmXEsLo+hIIu7D9XaBbQEvi7eVYNwmM8fX
G8vBShW7LhSBZ5ZYjP8sUZxKNTiK+0qmRzpEjubJlBKFimMHwJ7oq1Yez1Fc
MR+KVec8Mzo0QgdnZH5wBmdoj2EMcy6z1K1gLaqyR4fy1jVVvwD6lg4z2glZ
K+cmx9YNFyCcW7NCZcmX9hzB8ZHz0Ox6WFPHpTb5/jYQCAtjkJOM/ID0gm+U
4ikuWsFStOWOidhUhw3YGLCX2y6MZoxzo1ETnlF7JbtgqMYKHX6zp05152zl
mIBNJu4Z9Bwk8Rx8Hz6myWiBnZNNJ8hGzuycJMGM7ieZ4oZ0U7mk8Zdt4rhw
QtMYJnvO19o/sb2Kd+hgjox8GOyt6cyl3AtFtuBGmYAc94KJzwsVMhjRJ0vQ
3JnZQLYrzmeUKZx1tf+WW7m0Cd0QwwqWY2Aqrj/pVJyAHV8bVR5SNX04ayp/
NXDySqoyvykzELpN6tfMpAlIMAqKwp0kuGyqZTAVRLw9MrsLrb6BawKOAuno
EPc84l0OZeL9G0VLpa+J6U0UR5rXzsAANhEYJxKOy/s/BmGzTVRCNjBD1XnA
OAxEIgFwg0W666TYWgI8T2qsYWiuS5HU06HOdNxrqlLxJuEVrBQOOXnVKjz+
Z9as5LUqd4mjf7jrfrJoC+f4sofqxqErsQBi1Z/lKjgRNQIo7yuA4o8pgN5+
pmPG2ewu+XPEMcCHrrJc55usDMqvkKFdTa4od2QuTKK+pKcozncxgjdctbbG
bDZxQhTXw990NY5aWC64YlzMmHQcm84QwwBTvIbGy0HGdRvcZto2KC1IcP1C
sCb8zHVYxd5KFPm+AtX5UnS6wc4U/JniNFxOmlzj47wmGc88aD704O/Yt9sU
Z3t6jDda0f968HY90hB37GFQdEm8QQ95b8bLb3f8M5rh3J3fJPDXJlfFZ1B4
48E6OanKh0kWSuaZXFE+/IwiRuOvtIlcPBhECqaCSR2ElJvh0A6X5yZMSAAK
7m6DgxWUXSxRzhuAi7X7u32s55RGKKpPql/Ll5LyCjlJLT3tIWvfDTe3pFge
AGs2MRtzuiXM/Vb1lXNm781bdzpFwmvgtW9JlU2dizuwxtjeyRRinoMPxdrT
38odTdVTFQdpmLSE9cE3ErrOl31QiuZbom2Wn0fiGXtU/crE06cGone1zoev
MFn1ia0lHf2hm4IgYm/Rj2WLA3n88XbJCm00OMYLD9yZQ3O1CkgcZkcDfz3w
so9Ktac9mFoq+uyIvi7uql2Y/YbnnS6fXs6PFbRqhqU9JrMz5LwsrP53hfKA
fPm4U20nmcejeRVkEd5reXDwSr6E0V+TtvWHNe/G+A47C6sb8xj7VvFFBRSo
aY6RzKErmwXCU7ZNMTJ7laVdsDvLajfPZZsm89FmYMqf7ZeecXhNbXea2v5c
Gv9v5ZYNJNsmmjWhUMJgvAGDnwtjA3haBhSEIScp+Qh2vuNUumyDlF/9hSFC
QLCIBpMtiHfOgrOfbsyWqUsm51c+5KqlvFyHPjAiv5Gj85OufGnqCFq8lwKq
Kp4tEyD46wIx8hmROhiMoKe9JKPNRQ6gP3q7WITGFQ8gkq9oiO7u7kG3Q/9a
eBEDOMgL20B2X1doPsr3D3u7u5XXpoT7HQx2cXxEVARc4Gu32+l08GdYHdN2
6uWdetSpZzr1frljvr0HzbfXoX/V+fY2zre7Yb57Oep7hPqeQX1vw3z38077
1GnfdNr/xSiTspZ8wNUyLWIDVINIHrxf1uQieCPDnCY118C1TaLOqSV3vQy6
NyIPRuylP/YIlLsNaDDoSHGi0H8xL21jpBsqMYuOfdyzj3s2O1VABV0G7GL3
H81Br8DWqr/0W782q4ufl+hKIZC/Hx+9Atg5/V/2Ly7OB8d9vNbJezo8O2qP
zo/PLr1nvnOMWoLGki+9I8i8iK/edV/7Q4Hednx/x3C92uF6TcP1DEs0EKr3
mYTqPTmh9ppmtve7CLXfNNy+R6hgktwoq63rOZ3CB+Ff1gD6gE62L9CAg2JY
W1PckujjTJMV1u6wH2mNNNUVXIxHLXTk+xATDWEKA3YtWxTlkZV36Xm8Q0KZ
A+W5I0zRwDrOgl/N0j2MDWnaLRBzmO4afLYgdvlZrnKuCfnY97cZAY5kTUnP
VneLBJabBPV5Ngrx0CTme/Vb7+y5HCyQGpk4gBM3I98ZP48Ltd5CXKBby3VR
Jp+8x9nkAwk0PQSV1sFtHnjebx2as+T5dTEDl4PjjI+7U032MXtxSPFexwdi
580JJQOCxsX9HkX3ZMIYYMzAWOx1uDL41h6i9M6eBkXmup/sPaa8efccHL4C
u8dk/TsR/dXPe38rC0v/bpl76JCHdwy5VxqyWx6yMuLAsPTDBeQeuH8xYSkf
J0OLapIF00gFqSlVcJVDbivJj2lp1NKREBC1PZazzeVWwz9/anRkN5SmfLZD
W/RlwdpbbxY8rTdd49JSrmE3d2zh96FnOX+/Z/sQx3aDU+s7tG4+Lx3qr2sb
92ob5xacGcy5Y+b2wFxtWA3xNG5MAeV6W1JsQiU61IJqgF4VXB5zIeA2VY3s
3KVW7oTduwN2bxNsIi/IQ02VrK2wsCdNqkLhF2p6BZB+rZS5eEUAs7aJWzUw
Mknv0LsipCmI89n+AQx/X049DB3SQST73g1xr2S/OIp1leDNS0DpFP7rtYal
ZS832mud7rc2otprQrUcOW1EtbcRi2et0+d3ovpt6/QFNaouR89fjmHtcrz5
Vy7HkNYCVuTNhjlio31ckY2oPvVyIBbPcUUQi+bYBGWgtTGUw4F/Tzh3eIyC
POBbeqWnFYnEG1RRVQuW73wak4F+tetUielWCWIK8rMZZO/3gawEOgVp3Axy
714gu2WQlZi2wJabQe7/PpCVuLfA5Pfhr+YI+P781bs/f/W+IH89a509fzL+
2q0FaVXoF+Qvq0vuWOzeH1iZ3F/MHk2ZFMXsiyz2/VXmoymTosq8m7/+oMqk
KGafz18Vyv+/UCZFlem2g477Z31pXX57Rz7eH42xl7nBUZpmtFVoN3shvKcD
IRglcG6b9oPNXzK5NRXB5kJpHMKdDtjyxtZbMOQVXnW9LlbgEVd93S58vt7w
W9Ozr4X8WLzs8KM8w9oC8/lYuNzQPhs7t9A8wVF4y9m18T+llzUtzCiPNSO8
qNGD5DPOx5rz7B9l8eKAx8PFRpdcBnXy09MwC7I6LdAxV4cm6QMYp24q9yWz
hSvNLz7rVD93M84dV6zck3E+Z0Z4za2FU6y6rsflLsb5PFz2anAxifQvjst+
DS4mT/nFcfmuBhf/uoAvg4sv3G0u2nlCk9AejsfnYwOBK69I+HjjlYQIpB5P
jDnJNyeVpKnv4epCnWsG+/cM8tyuwmEfXU941Uv2l6pB8FesRk88Fi7dXQ8O
lfe3ZU15/xfh5DIuzwGXxjK4BlwK6tD9YvYB6qlbefKIM/rOg0PFZzijhuKz
p6ZuCZcXhIt/VrFEl6fWE3y/iy3ubfzzDrWaY5oq3GdhTVEQclIrMZ3zgWER
huBdpqR8csCcHWrJKV8YsuUQKrTBS2a3Oo+sAg7DLCf0ERXVc5lo/edJVcBu
u9tzcN7Gri6lEZenZNI9D86uuV/eFrKaKxzxcDKqpiZcSiqg+QadvE1ljo84
o30PzuEjz8jbGC2t0VPO6JkH590jz8iri/hCM6pVR2T23F8ncH+c4JF1kReI
vb0cutthK/qo1I6x+bdO8nF5Up3UtiwP8b/h9/PKjfBPj8sdhjO/t/cJjWau
cWr4tK7ZH51N8zjwX82mvlq2hmbkHf75UrjcwaYbLrH8TL6dO77VVcYtGf8a
7t3Y/o/Oxv+PtK0H58SwcfF+ui+Hi++7nRlcilcD/mvEe2xw8W9v/LLiLfG4
0SrFKK28HwCwzvA+IVsImIX8Z0Kl7E/fx8ktSN0VVQ5T08vrAC/uA0k+uk5X
N/D/ZMapGBgz4GwO1p6t6FoYHmeAfwgdPbMk1W5LqR/PUtAPFxn+bWvC4X0Y
EIjhIgijAxwJGnQ0Nvg+xredabKg7v8H6SGMgOSGAAA=

-->

</rfc>

